{
    "Ar36": {
        "error": 1.9565684782031326e-07,
        "error_type": "SEM",
        "filter_outliers_dict": {
            "filter_outliers": true,
            "iterations": 1,
            "std_devs": 2
        },
        "fit": "linear",
        "value": 0.00023964294347253296
    },
    "Ar37": {
        "error": 2.2688047384213098e-06,
        "error_type": "SEM",
        "filter_outliers_dict": {
            "filter_outliers": true,
            "iterations": 1,
            "std_devs": 2
        },
        "fit": "linear",
        "value": 0.0016737672198418995
    },
    "Ar38": {
        "error": 4.3002927045595703e-07,
        "error_type": "SEM",
        "filter_outliers_dict": {
            "filter_outliers": true,
            "iterations": 1,
            "std_devs": 2
        },
        "fit": "linear",
        "value": 0.00018989797907766238
    },
    "Ar39": {
        "error": 1.3880322466314282e-05,
        "error_type": "SEM",
        "filter_outliers_dict": {
            "filter_outliers": true,
            "iterations": 1,
            "std_devs": 2
        },
        "fit": "linear",
        "value": 0.011350757172598237
    },
    "Ar40": {
        "error": 1.919209963169793e-05,
        "error_type": "SEM",
        "filter_outliers_dict": {
            "filter_outliers": true,
            "iterations": 1,
            "std_devs": 2
        },
        "fit": "parabolic",
        "value": 0.0981947210486192
    }
}